wordpress_setup.py
wordpress_docker_setup-1.9.0.dist-info/LICENSE
wordpress_docker_setup-1.9.0.dist-info/METADATA
wordpress_docker_setup-1.9.0.dist-info/WHEEL
wordpress_docker_setup-1.9.0.dist-info/entry_points.txt
wordpress_docker_setup-1.9.0.dist-info/top_level.txt
wordpress_docker_setup-1.9.0.dist-info/RECORD
