Metadata-Version: 2.1
Name: wordpress-docker-setup
Version: 1.9.0
Summary: This is a script to create a docker-compose project for a wordpress site with a nginx reverse proxy. The script will create the configuration files for the project and start the containers as well as install the nginx reverse proxy configuration. *See the usage section for more information.*
Author-email: Frederik Beimgraben <frederik@beimgraben.net>
Maintainer-email: Frederik Beimgraben <frederik@beimgraben.net>
Project-URL: Homepage, https://github.com/frederikbeimgraben/Wordpress-Installation-Script
Project-URL: Repository, https://github.com/frederikbeimgraben/Wordpress-Installation-Script
Project-URL: Issues, https://github.com/frederikbeimgraben/Wordpress-Installation-Script/issues
Keywords: wordpress,docker,nginx,reverse proxy,script,setup,configuration
Classifier: Programming Language :: Python :: 3
Classifier: License :: OSI Approved :: GNU General Public License v3 (GPLv3)
Classifier: Operating System :: POSIX :: Linux
Classifier: Environment :: Console
Classifier: Natural Language :: English
Requires-Python: >=3.8
License-File: LICENSE
Requires-Dist: requests
Requires-Dist: argparse
